recently_played_playlists/__init__.py
recently_played_playlists/api/__init__.py
recently_played_playlists/api/api.py
recently_played_playlists/cli/__init__.py
recently_played_playlists/cli/main.py
recently_played_playlists/db/__init__.py
recently_played_playlists/db/db.py
recently_played_playlists/spotify/__init__.py
recently_played_playlists/spotify/save_recently_played_tracks.py
recently_played_playlists/spotify/util.py
recently_played_playlists-1.0.1.dist-info/DESCRIPTION.rst
recently_played_playlists-1.0.1.dist-info/METADATA
recently_played_playlists-1.0.1.dist-info/RECORD
recently_played_playlists-1.0.1.dist-info/WHEEL
recently_played_playlists-1.0.1.dist-info/entry_points.txt
recently_played_playlists-1.0.1.dist-info/metadata.json
recently_played_playlists-1.0.1.dist-info/top_level.txt
